gym_cabworld/__init__.py
gym_cabworld/data/map.dat
gym_cabworld/data/small_map.dat
gym_cabworld/envs/__init__.py
gym_cabworld/envs/cab_model.py
gym_cabworld/envs/custom_env.py
gym_cabworld/envs/game.py
gym_cabworld/envs/game_multi_agent.py
gym_cabworld/envs/map_model.py
gym_cabworld/envs/passenger_model.py
gym_cabworld/images/cab.png
gym_cabworld/images/map_gen.png
gym_cabworld/images/person_1.png
gym_cabworld/images/person_2.png
gym_cabworld/images/person_3.png
gym_cabworld/images/small_map_gen.png
gym_cabworld-2.0.1.dist-info/LICENSE.md
gym_cabworld-2.0.1.dist-info/METADATA
gym_cabworld-2.0.1.dist-info/WHEEL
gym_cabworld-2.0.1.dist-info/top_level.txt
gym_cabworld-2.0.1.dist-info/RECORD
