Metadata-Version: 2.1
Name: gym-cabworld
Version: 2.0.1
Summary: Cabworld Reinforcement Environment
Home-page: UNKNOWN
Author: Nikolai Limbrunner
Author-email: nikolai.limbrunner@web.de
License: UNKNOWN
Platform: UNKNOWN
Requires-Dist: gym
Requires-Dist: pygame
Requires-Dist: wheel
